degiroapi/__init__.py
degiroapi/client_info.py
degiroapi/datatypes.py
degiroapi/intervaltypes.py
degiroapi/order.py
degiroapi/product.py
degiroapi/utils.py
degiroxxx-0.0.1.dist-info/LICENSE
degiroxxx-0.0.1.dist-info/METADATA
degiroxxx-0.0.1.dist-info/WHEEL
degiroxxx-0.0.1.dist-info/top_level.txt
degiroxxx-0.0.1.dist-info/RECORD
