Metadata-Version: 2.1
Name: degiroxxx
Version: 0.0.1
Summary: Degiroxxx
Home-page: https://github.com/gregory798/degiroxxx/
Author: xxx
Author-email: xxxxxxxxxxxxxxxxxxxx@gmail.com
Classifier: Programming Language :: Python :: 3
Classifier: License :: OSI Approved :: MIT License
Classifier: Operating System :: OS Independent
Requires-Python: >=3.6
License-File: LICENSE
